finance_datareader_py/__init__.py
finance_datareader_py/_version.py
finance_datareader_py/csindex/__init__.py
finance_datareader_py/csrc/__init__.py
finance_datareader_py/csrc/category.py
finance_datareader_py/eastmoney/__init__.py
finance_datareader_py/eastmoney/daily.py
finance_datareader_py/gtimg/__init__.py
finance_datareader_py/gtimg/daily.py
finance_datareader_py/gtimg/daily_details.py
finance_datareader_py/hexun/__init__.py
finance_datareader_py/netease/__init__.py
finance_datareader_py/netease/daily.py
finance_datareader_py/sina/__init__.py
finance_datareader_py/sina/daily_details.py
finance_datareader_py/sohu/__init__.py
finance_datareader_py/sohu/daily.py
finance_datareader_py/sse/__init__.py
finance_datareader_py/szse/__init__.py
finance_datareader_py/tests/__init__.py
finance_datareader_py/tests/test_init.py
finance_datareader_py/tests/csindex/__init__.py
finance_datareader_py/tests/csindex/test_init.py
finance_datareader_py/tests/csrc/__init__.py
finance_datareader_py/tests/csrc/test_category.py
finance_datareader_py/tests/easemoney/__init__.py
finance_datareader_py/tests/easemoney/test_daily.py
finance_datareader_py/tests/gtimg/__init__.py
finance_datareader_py/tests/gtimg/test_daily.py
finance_datareader_py/tests/gtimg/test_dailydetails.py
finance_datareader_py/tests/hexun/__init__.py
finance_datareader_py/tests/hexun/test_init.py
finance_datareader_py/tests/netease/__init__.py
finance_datareader_py/tests/netease/test_daily.py
finance_datareader_py/tests/netease/test_init.py
finance_datareader_py/tests/sina/__init__.py
finance_datareader_py/tests/sina/test_dailydetails.py
finance_datareader_py/tests/sina/test_init.py
finance_datareader_py/tests/sohu/__init__.py
finance_datareader_py/tests/sohu/test_daily.py
finance_datareader_py/tests/sohu/test_init.py
finance_datareader_py/tests/sse/__init__.py
finance_datareader_py/tests/sse/test_init.py
finance_datareader_py/tests/szse/__init__.py
finance_datareader_py-0.2.10.dist-info/DESCRIPTION.rst
finance_datareader_py-0.2.10.dist-info/METADATA
finance_datareader_py-0.2.10.dist-info/RECORD
finance_datareader_py-0.2.10.dist-info/WHEEL
finance_datareader_py-0.2.10.dist-info/metadata.json
finance_datareader_py-0.2.10.dist-info/top_level.txt
