Metadata-Version: 1.1
Name: finance-datareader-py
Version: 0.2.10
Summary: Python 金融数据读取器
